pytui/__init__.py
pytui/common.py
pytui/logging_tools.py
pytui/plugin.py
pytui/runner.py
pytui/settings.py
pytui/test_pytest_django_fail.py
pytui/ui.py
pytest_ui-0.5.dist-info/LICENSE
pytest_ui-0.5.dist-info/METADATA
pytest_ui-0.5.dist-info/WHEEL
pytest_ui-0.5.dist-info/entry_points.txt
pytest_ui-0.5.dist-info/top_level.txt
pytest_ui-0.5.dist-info/RECORD
